advseglearn/__init__.py
advseglearn/adversarial_loss.py
advseglearn/combined_dataset.py
advseglearn/discriminator_loss.py
advseglearn/mixed_activation.py
advseglearn/multiclass_dataset.py
advseglearn/semi_supervised_loss.py
advseglearn/testRun.py
advseglearn/testUnet.py
advseglearn/train_GAN.py
advseglearn/train_model.py
advseglearn/unet.py
advseglearn-1.0.5.dist-info/licenses/LICENSE
advseglearn-1.0.5.dist-info/METADATA
advseglearn-1.0.5.dist-info/WHEEL
advseglearn-1.0.5.dist-info/top_level.txt
advseglearn-1.0.5.dist-info/RECORD
