Metadata-Version: 2.4
Name: AdvSegLearn
Version: 1.0.5
Summary: Package for combining traditional and adversarial learning.
Author-email: Anthony Lino <aml334@case.edu>
License-Expression: MIT
Project-URL: Homepage, https://github.com/anthony-lino/
Classifier: Programming Language :: Python :: 3
Classifier: Operating System :: OS Independent
Requires-Python: >=3.7
License-File: LICENSE
Requires-Dist: torch
Requires-Dist: numpy
Requires-Dist: pandas
Requires-Dist: scikit-image
Requires-Dist: torchvision
Requires-Dist: matplotlib
Requires-Dist: opencv-python
Requires-Dist: Pillow
Dynamic: license-file
